{
    "name": "useblock",
    "desc": "Uses the block at the specified coordinates.",
    "parameters": [
        {
            "name": "x",
            "desc": "The X coordinate of the block.",
            "type": "int",
            "parameters": [
                {
                    "name": "y",
                    "desc": "The Y coordinate of the block.",
                    "type": "int",
                    "parameters": [
                        {
                            "name": "z",
                            "desc": "The Z coordinate of the block.",
                            "type": "int"
                        }
                    ]
                }
            ]
        }
    ]
}